components/__init__.py
components/exchange.py
components/inflation.py
components/settings.py
components/update.py
components/utils.py
data/__init__.py
CuCoPyAnnotationDemo-1.1.dist-info/METADATA
CuCoPyAnnotationDemo-1.1.dist-info/WHEEL
CuCoPyAnnotationDemo-1.1.dist-info/top_level.txt
CuCoPyAnnotationDemo-1.1.dist-info/RECORD
