Metadata-Version: 2.1
Name: CuCoPyAnnotationDemo
Version: 1.1
Summary: UNKNOWN
Home-page: https://github.com/FZJ-IEK3-VSA/CuCoPyAnnotationDemo
Author: Julian Schoenau
Author-email: j.schoenau@fz-juelich.de
License: MIT
Keywords: finance,conversion
Platform: UNKNOWN
